{"bugs": {"661271": {"comments": [{"bug_id": 661271, "tags": [], "is_private": false, "count": 0, "id": 5506442, "text": "User-Agent:       Mozilla/5.0 (X11; U; Linux x86_64; en-US; rv:1.9.2.9) Gecko/20110522 Red Hat/3.6.9-2.el6 Firefox/3.6.9\nBuild Identifier: 3.3a4pre (2011-06-01)\n\nthe Message Filters do not have an action item that allows an incoming email to be archived.\n\nReproducible: Always\n\nSteps to Reproduce:\nSetup a new Message Filter\n\nSelect criteria to match against\n\n\nActual Results:  \nIn the actions its possible to delete, move it, copy it, change various flags etc but not to archive the email.\n\nExpected Results:  \nIt would be great if an option can be added to the actions list that would archive the email, and honour the granularity settings for that mailbox.", "time": "2011-06-01T16:45:56Z", "attachment_id": null, "creation_time": "2011-06-01T16:45:56Z", "raw_text": "User-Agent:       Mozilla/5.0 (X11; U; Linux x86_64; en-US; rv:1.9.2.9) Gecko/20110522 Red Hat/3.6.9-2.el6 Firefox/3.6.9\nBuild Identifier: 3.3a4pre (2011-06-01)\n\nthe Message Filters do not have an action item that allows an incoming email to be archived.\n\nReproducible: Always\n\nSteps to Reproduce:\nSetup a new Message Filter\n\nSelect criteria to match against\n\n\nActual Results:  \nIn the actions its possible to delete, move it, copy it, change various flags etc but not to archive the email.\n\nExpected Results:  \nIt would be great if an option can be added to the actions list that would archive the email, and honour the granularity settings for that mailbox.", "creator": "kbsingh@karan.org", "author": "kbsingh@karan.org"}, {"id": 5828690, "tags": ["me-too"], "count": 1, "is_private": false, "bug_id": 661271, "raw_text": "This new feature of the filter is essential for those who have to store the mail.\n+1", "creation_time": "2011-11-05T19:03:53Z", "author": "dapinna@gmail.com", "attachment_id": null, "time": "2011-11-05T19:03:53Z", "text": "This new feature of the filter is essential for those who have to store the mail.\n+1", "creator": "dapinna@gmail.com"}, {"creator": "acelists@atlas.sk", "author": "acelists@atlas.sk", "text": "*** Bug 996130 has been marked as a duplicate of this bug. ***", "attachment_id": null, "time": "2014-04-17T06:30:14Z", "raw_text": "", "creation_time": "2014-04-17T06:30:14Z", "bug_id": 661271, "is_private": false, "count": 2, "tags": [], "id": 8674775}, {"id": 8680115, "tags": ["me-too"], "is_private": false, "count": 3, "bug_id": 661271, "creation_time": "2014-04-18T02:02:23Z", "raw_text": "+1\nI think this feature would be great. In fact it will make the archiving function much more functional.", "author": "jose.goni@gmail.com", "attachment_id": null, "time": "2014-04-18T02:02:23Z", "creator": "jose.goni@gmail.com", "text": "+1\nI think this feature would be great. In fact it will make the archiving function much more functional."}, {"creator": "smolejv@gmx.net", "author": "smolejv@gmx.net", "tags": ["me-too"], "count": 4, "is_private": false, "id": 8725475, "bug_id": 661271, "raw_text": "+1\n\nsmo", "creation_time": "2014-04-29T12:11:33Z", "text": "+1\n\nsmo", "attachment_id": null, "time": "2014-04-29T12:11:33Z"}, {"author": "okelet@gmail.com", "creator": "okelet@gmail.com", "creation_time": "2015-03-23T16:28:14Z", "raw_text": "+1, please!!!!", "attachment_id": null, "time": "2015-03-23T16:28:14Z", "text": "+1, please!!!!", "id": 10065083, "tags": ["me-too"], "count": 5, "is_private": false, "bug_id": 661271}, {"author": "brad@wcubed.net", "creator": "brad@wcubed.net", "attachment_id": null, "time": "2015-07-20T18:10:21Z", "text": "I'm rather surprised that this functionality wasn't included already. Please add it soon. I would expect it to be relatively simple to do so...", "creation_time": "2015-07-20T18:10:21Z", "raw_text": "I'm rather surprised that this functionality wasn't included already. Please add it soon. I would expect it to be relatively simple to do so...", "bug_id": 661271, "id": 10515264, "tags": ["me-too"], "is_private": false, "count": 6}, {"author": "imdad.sk@gmail.com", "creator": "imdad.sk@gmail.com", "id": 11036557, "count": 7, "is_private": false, "tags": ["me-too"], "bug_id": 661271, "raw_text": "As I have multiple IMAP accounts setup in my Thunderbird it goes slow many times. I do archiving manually which is time taking task. Automating archiving through filters would be great feature to include in to Thunderbird.\nI see this bug is not assigned to anyone yet. I hope this will be assigned to someone soon as when finished this feature will be used by many users.", "creation_time": "2015-12-30T08:03:38Z", "time": "2015-12-30T08:03:38Z", "attachment_id": null, "text": "As I have multiple IMAP accounts setup in my Thunderbird it goes slow many times. I do archiving manually which is time taking task. Automating archiving through filters would be great feature to include in to Thunderbird.\nI see this bug is not assigned to anyone yet. I hope this will be assigned to someone soon as when finished this feature will be used by many users."}, {"author": "poehler@interworx.com", "creator": "poehler@interworx.com", "time": "2016-02-17T20:53:05Z", "attachment_id": null, "text": "+1 pls", "creation_time": "2016-02-17T20:53:05Z", "raw_text": "+1 pls", "bug_id": 661271, "id": 11173443, "count": 8, "is_private": false, "tags": ["me-too"]}, {"author": "edouard@e-gaulue.com", "creator": "edouard@e-gaulue.com", "creation_time": "2016-03-03T11:15:41Z", "raw_text": "+100. As an instructor, most of my students ask for why it's not there.", "time": "2016-03-03T11:15:41Z", "attachment_id": null, "text": "+100. As an instructor, most of my students ask for why it's not there.", "id": 11214567, "tags": [], "count": 9, "is_private": false, "bug_id": 661271}, {"text": "+100", "time": "2018-11-12T12:09:08Z", "attachment_id": null, "creation_time": "2018-11-12T12:09:08Z", "raw_text": "+100", "bug_id": 661271, "count": 10, "is_private": false, "tags": [], "id": 13751623, "creator": "ts@websafe.pl", "author": "ts@websafe.pl"}, {"author": "chw368@gmail.com", "creator": "chw368@gmail.com", "id": 14987205, "tags": [], "count": 11, "is_private": false, "bug_id": 661271, "raw_text": "+100", "creation_time": "2020-08-13T04:01:54Z", "attachment_id": null, "time": "2020-08-13T04:01:54Z", "text": "+100"}]}}, "comments": {}}