{"bugs": [{"id": 650613, "history": [{"who": "martindrummer@libero.it", "changes": [{"field_name": "url", "added": "http://www.uz-translations.net/", "removed": "http://www.uz-translations.net/http://"}], "when": "2011-04-17T08:34:13Z"}, {"who": "fmdevelopertim@gmail.com", "changes": [{"added": "fmdevelopertim@gmail.com", "removed": "", "field_name": "cc"}], "when": "2011-04-17T20:37:05Z"}, {"who": "fmdevelopertim@gmail.com", "changes": [{"field_name": "version", "added": "4.0 Branch", "removed": "unspecified"}], "when": "2011-04-18T02:24:04Z"}, {"when": "2011-04-20T08:24:34Z", "changes": [{"field_name": "cc", "removed": "", "added": "vlad.ghetiu@softvision.ro"}], "who": "vlad.ghetiu@softvision.ro"}, {"changes": [{"added": "NEW", "removed": "UNCONFIRMED", "field_name": "status"}, {"field_name": "is_confirmed", "removed": "0", "added": "1"}], "when": "2011-06-16T07:10:06Z", "who": "vlad.ghetiu@softvision.ro"}], "alias": null}]}