{"bugs": [{"alias": null, "id": 650775, "history": [{"when": "2011-04-18T13:50:38Z", "changes": [{"field_name": "depends_on", "removed": "", "added": "650776"}], "who": "hsivonen@mozilla.com"}, {"when": "2011-04-18T14:10:32Z", "changes": [{"field_name": "depends_on", "removed": "", "added": "650784"}], "who": "hsivonen@mozilla.com"}, {"when": "2011-04-18T14:18:04Z", "changes": [{"added": "650787", "removed": "", "field_name": "depends_on"}], "who": "hsivonen@mozilla.com"}, {"who": "matjk7@gmail.com", "changes": [{"added": "matjk7@gmail.com", "field_name": "cc", "removed": ""}], "when": "2011-04-18T14:37:20Z"}, {"changes": [{"added": "VYV03354@nifty.ne.jp", "field_name": "cc", "removed": ""}], "who": "VYV03354@nifty.ne.jp", "when": "2011-04-18T14:47:59Z"}, {"who": "ryanvm@gmail.com", "changes": [{"added": "ryanvm@gmail.com", "removed": "", "field_name": "cc"}], "when": "2011-04-18T16:36:31Z"}, {"who": "hsivonen@mozilla.com", "changes": [{"added": "651045", "field_name": "blocks", "removed": ""}], "when": "2011-04-19T07:52:24Z"}, {"changes": [{"added": "482911", "removed": "", "field_name": "depends_on"}], "who": "hsivonen@mozilla.com", "when": "2011-04-19T09:34:40Z"}, {"changes": [{"added": "Remove CNavDTD and nsHTMLTokenizer from the tree", "field_name": "summary", "removed": "Remove CNavDTD from the tree"}], "who": "hsivonen@mozilla.com", "when": "2011-04-19T12:13:57Z"}, {"when": "2011-04-19T12:20:50Z", "who": "hsivonen@mozilla.com", "changes": [{"added": "651096", "removed": "", "field_name": "blocks"}]}, {"when": "2011-05-09T13:13:17Z", "who": "fullmetaljacket.xp+bugmail@gmail.com", "changes": [{"field_name": "cc", "removed": "", "added": "fullmetaljacket.xp+bugmail@gmail.com"}]}, {"when": "2012-03-15T20:55:06Z", "changes": [{"removed": "", "field_name": "cc", "added": "dbcooper.nz@gmail.com"}], "who": "dbcooper.nz@gmail.com"}, {"when": "2020-12-14T17:07:02Z", "who": "jstutte@mozilla.com", "changes": [{"field_name": "priority", "removed": "--", "added": "P5"}, {"field_name": "severity", "removed": "normal", "added": "S4"}]}]}]}