{"bugs": [{"id": 693353, "alias": null, "history": [{"changes": [{"added": "m-wada@japan.com", "field_name": "cc", "removed": ""}], "when": "2011-10-10T18:47:28Z", "who": "m-wada@usa.com"}, {"when": "2011-10-11T13:16:29Z", "who": "acelists@atlas.sk", "changes": [{"field_name": "cc", "added": "acelists@atlas.sk", "removed": ""}]}, {"when": "2012-01-04T19:31:45Z", "who": "vseerror@lehigh.edu", "changes": [{"field_name": "whiteboard", "added": "[closeme 2012-01-21]", "removed": ""}, {"removed": "normal", "added": "major", "field_name": "severity"}]}, {"changes": [{"field_name": "depends_on", "added": "522675", "removed": ""}], "who": "m-wada@usa.com", "when": "2012-01-05T07:42:57Z"}, {"who": "m-wada@usa.com", "when": "2012-01-17T01:02:08Z", "changes": [{"removed": "", "field_name": "keywords", "added": "dataloss"}, {"removed": "UNCONFIRMED", "added": "NEW", "field_name": "status"}, {"field_name": "component", "added": "Networking: IMAP", "removed": "General"}, {"removed": "Thunderbird", "field_name": "product", "added": "MailNews Core"}, {"removed": "general@thunderbird.bugs", "added": "networking.imap@mail.bugs", "field_name": "qa_contact"}, {"added": "1", "field_name": "is_confirmed", "removed": "0"}, {"removed": "Windows XP", "added": "All", "field_name": "op_sys"}]}, {"changes": [{"field_name": "summary", "added": "Message disappears from Inbox after unsuccessful detach operation (Even though APPEND is rejected by NO response, Tb sends mail data to server and is rejected by BAD, and even after NO/BAD, Tb goes ahead to following \"UID xx STORE Flags \\Deleted\" step)", "removed": "Message disappears from Inbox after unsuccessful detach operation"}], "when": "2012-01-17T01:10:27Z", "who": "m-wada@usa.com"}, {"changes": [{"added": "vseerror@lehigh.edu", "field_name": "cc", "removed": ""}, {"removed": "[closeme 2012-01-21]", "added": "", "field_name": "whiteboard"}], "who": "vseerror@lehigh.edu", "when": "2012-01-18T11:33:17Z"}, {"changes": [{"removed": "", "field_name": "blocks", "added": "720158"}], "when": "2012-01-23T05:17:39Z", "who": "m-wada@usa.com"}, {"who": "vseerror@lehigh.edu", "when": "2014-02-07T14:12:22Z", "changes": [{"added": "critical", "field_name": "severity", "removed": "major"}]}, {"changes": [{"added": "1079280", "field_name": "depends_on", "removed": ""}], "who": "m-wada@usa.com", "when": "2014-10-08T08:09:22Z"}, {"changes": [{"removed": "", "added": "matafagafo@yahoo.com", "field_name": "cc"}], "who": "matafagafo@yahoo.com", "when": "2021-12-21T10:20:32Z"}]}]}