{"faults": [], "bugs": [{"is_open": true, "qa_contact": "", "op_sys": "macOS", "assigned_to": "vadimk@utest.com", "dupe_of": null, "last_change_time": "2011-10-12T23:41:12Z", "flags": [], "creator_detail": {"nick": "camd", "name": "cameron@dawsoncode.com", "email": "cameron@dawsoncode.com", "real_name": "Cameron Dawson [:camd]", "id": 392439}, "priority": "--", "depends_on": [], "comment_count": 1, "creator": "cameron@dawsoncode.com", "is_cc_accessible": true, "keywords": [], "cc": [], "cf_user_story": "", "duplicates": [], "cf_fx_points": "---", "classification": "Other", "regressed_by": [], "assigned_to_detail": {"id": 407526, "email": "vadimk@utest.com", "real_name": "Vadim", "nick": "vadimk", "name": "vadimk@utest.com"}, "id": 694189, "see_also": [], "alias": null, "whiteboard": "", "version": "unspecified", "status": "NEW", "type": "defect", "votes": 0, "component": "Case Conductor-Platform", "resolution": "", "target_milestone": "---", "cf_last_resolved": null, "creation_time": "2011-10-12T23:41:12Z", "groups": [], "severity": "normal", "is_confirmed": true, "regressions": [], "cc_detail": [], "summary": "hit error deleting a test case", "platform": "x86", "url": "", "product": "Mozilla QA", "is_creator_accessible": true, "mentors_detail": [], "mentors": [], "cf_qa_whiteboard": "", "blocks": [], "cf_fx_iteration": "---"}]}