{"faults": [], "bugs": [{"is_cc_accessible": true, "cf_tracking_seamonkey257esr": "---", "cf_fx_iteration": "---", "assigned_to_detail": {"nick": "nobody", "real_name": "Nobody; OK to take it and work on it", "email": "nobody@mozilla.org", "name": "nobody@mozilla.org", "id": 1}, "is_confirmed": true, "status": "NEW", "depends_on": [], "is_creator_accessible": true, "type": "defect", "groups": [], "cf_last_resolved": null, "assigned_to": "nobody@mozilla.org", "votes": 0, "last_change_time": "2015-04-25T11:12:14Z", "creator_detail": {"nick": "InvisibleSmiley", "email": "jh@junetz.de", "real_name": "Jens Hatlak (:InvisibleSmiley)", "name": "jh@junetz.de", "id": 25926}, "cf_status_seamonkey253": "---", "priority": "--", "mentors": [], "alias": null, "cf_user_story": "", "product": "SeaMonkey", "version": "Trunk", "component": "MailNews: Message Display", "id": 638915, "cf_tracking_seamonkey253": "---", "url": "", "whiteboard": "", "op_sys": "All", "regressions": [], "platform": "All", "keywords": [], "summary": "[tabmail] \"Error: this.browsers[i] is undefined\" when loading a feed message in the message pane [tabbrowser.xml onLinkAdded method]", "cc_detail": [{"nick": "mmokrejs", "email": "mmokrejs@gmail.com", "real_name": "Martin Mokrejs", "id": 66576, "name": "mmokrejs@gmail.com"}, {"name": "philip.chee@gmail.com", "id": 188891, "email": "philip.chee@gmail.com", "real_name": "Philip Chee", "nick": "philip.chee"}, {"name": "u331436@disabled.tld", "id": 331436, "nick": "u331436", "real_name": "", "email": "u331436@disabled.tld"}], "duplicates": [], "comment_count": 3, "cf_status_seamonkey257esr": "---", "cc": ["mmokrejs@gmail.com", "philip.chee@gmail.com", "u331436@disabled.tld"], "cf_crash_signature": "", "qa_contact": "", "target_milestone": "---", "severity": "normal", "cf_fx_points": "---", "resolution": "", "creation_time": "2011-03-04T20:50:18Z", "cf_qa_whiteboard": "", "flags": [], "classification": "Client Software", "blocks": [], "regressed_by": [], "dupe_of": null, "is_open": true, "mentors_detail": [], "see_also": [], "creator": "jh@junetz.de"}]}