{"bugs": [{"op_sys": "Windows 7", "mentors_detail": [], "creator_detail": {"real_name": "Jeremy Lawrence", "nick": "j", "id": 92928, "email": "j@lawrence.net", "name": "j@lawrence.net"}, "comment_count": 4, "keywords": [], "cf_status_thunderbird_97": "---", "product": "Calendar", "cf_status_thunderbird_98": "---", "version": "unspecified", "status": "UNCONFIRMED", "cf_tracking_thunderbird_esr91": "---", "assigned_to": "nobody@mozilla.org", "regressed_by": [], "summary": "An event copied from a specific calendar (not Home) should paste to the same calendar. It goes to Home instead.", "target_milestone": "---", "duplicates": [], "whiteboard": "", "is_cc_accessible": true, "cf_tracking_thunderbird_96": "---", "is_creator_accessible": true, "creator": "j@lawrence.net", "mentors": [], "severity": "normal", "cf_tracking_thunderbird_98": "---", "cf_last_resolved": null, "is_open": true, "qa_contact": "", "cc": ["larsen007@web.de", "starko@chello.nl"], "priority": "--", "is_confirmed": false, "groups": [], "depends_on": [], "platform": "x86", "type": "defect", "cc_detail": [{"name": "larsen007@web.de", "email": "larsen007@web.de", "id": 299765, "real_name": "Larsen", "nick": "larsen007"}, {"nick": "starko", "real_name": "Starko", "id": 364783, "email": "starko@chello.nl", "name": "starko@chello.nl"}], "cf_tracking_thunderbird_97": "---", "classification": "Client Software", "id": 632374, "assigned_to_detail": {"real_name": "Nobody; OK to take it and work on it", "nick": "nobody", "id": 1, "email": "nobody@mozilla.org", "name": "nobody@mozilla.org"}, "cf_qa_whiteboard": "", "creation_time": "2011-02-08T14:35:59Z", "blocks": [], "cf_fx_iteration": "---", "cf_fx_points": "---", "alias": null, "cf_crash_signature": "", "votes": 1, "component": "General", "url": "", "see_also": [], "cf_status_thunderbird_esr91": "---", "last_change_time": "2013-09-07T16:16:53Z", "regressions": [], "resolution": "", "cf_status_thunderbird_96": "---", "flags": [], "cf_user_story": "", "dupe_of": null}], "faults": []}