{"faults": [], "bugs": [{"cf_crash_signature": "", "cf_last_resolved": null, "creation_time": "2011-08-17T20:10:50Z", "groups": [], "severity": "normal", "is_confirmed": false, "regressions": [], "cf_tracking_thunderbird_98": "---", "status": "UNCONFIRMED", "type": "defect", "votes": 0, "component": "Mail Window Front End", "resolution": "", "target_milestone": "---", "mentors_detail": [], "mentors": [], "cf_qa_whiteboard": "", "cf_status_thunderbird_96": "---", "blocks": [], "cf_fx_iteration": "---", "cf_tracking_thunderbird_97": "---", "cc_detail": [{"id": 63681, "real_name": "Daniel Kabs, reporting bugs since 2002", "email": "bugzilla@kabsi.de", "name": "bugzilla@kabsi.de", "nick": "bugzilla"}, {"name": "vseerror@lehigh.edu", "nick": "wsmwk", "id": 29811, "real_name": "Wayne Mery (:wsmwk)", "email": "vseerror@lehigh.edu"}], "summary": "Tag colors randomly not shown in message pane because of color selector mismatch", "platform": "x86_64", "url": "", "product": "Thunderbird", "is_creator_accessible": true, "creator_detail": {"real_name": "Peer Tavori", "email": "petav@gmx.de", "id": 279648, "name": "petav@gmx.de", "nick": "petav"}, "priority": "--", "depends_on": [], "comment_count": 2, "creator": "petav@gmx.de", "is_cc_accessible": true, "keywords": [], "cc": ["bugzilla@kabsi.de", "vseerror@lehigh.edu"], "is_open": true, "qa_contact": "", "cf_tracking_thunderbird_esr91": "---", "op_sys": "Windows 7", "assigned_to": "nobody@mozilla.org", "dupe_of": null, "cf_status_thunderbird_98": "---", "last_change_time": "2015-12-01T23:47:55Z", "flags": [], "cf_status_thunderbird_97": "---", "regressed_by": [], "cf_status_thunderbird_esr91": "---", "assigned_to_detail": {"name": "nobody@mozilla.org", "nick": "nobody", "real_name": "Nobody; OK to take it and work on it", "email": "nobody@mozilla.org", "id": 1}, "id": 679844, "alias": null, "see_also": [], "whiteboard": "", "version": "6 Branch", "cf_user_story": "", "duplicates": [], "cf_tracking_thunderbird_96": "---", "classification": "Client Software", "cf_fx_points": "---"}]}