{"bugs": [{"history": [{"when": "2011-04-06T18:51:02Z", "changes": [{"removed": "", "added": "ryan@mozillafoundation.org", "field_name": "cc"}], "who": "cnovak@mozilla.com"}, {"who": "cnovak@mozilla.com", "changes": [{"field_name": "cc", "removed": "", "added": "chelsea@mozillafoundation.org"}], "when": "2011-04-06T18:51:57Z"}, {"who": "ryan@mozillafoundation.org", "when": "2011-04-13T20:14:59Z", "changes": [{"field_name": "blocks", "removed": "", "added": "649698"}]}, {"when": "2011-08-04T15:39:41Z", "changes": [{"field_name": "component", "removed": "www.mozilla.org", "added": "donate.mozilla.org"}, {"added": "donate-mozilla-org@website.bugs", "removed": "www-mozilla-org@website.bugs", "field_name": "qa_contact"}], "who": "davidwboswell@yahoo.com"}, {"when": "2011-09-20T21:11:53Z", "changes": [{"field_name": "cc", "added": "", "removed": "cnovak@mozilla.com"}], "who": "cnovak@mozilla.com"}], "id": 641363, "alias": null}]}