{"comments": {}, "bugs": {"697697": {"comments": [{"raw_text": "This may be useful to check if expiration is too slow. nsPlacesExpiration.js already knows this number.", "creation_time": "2011-10-27T12:58:50Z", "text": "This may be useful to check if expiration is too slow. nsPlacesExpiration.js already knows this number.", "attachment_id": null, "time": "2011-10-27T12:58:50Z", "tags": [], "count": 0, "is_private": false, "id": 5808621, "bug_id": 697697, "creator": "mak@mozilla.com", "author": "mak@mozilla.com"}]}}}