{"bugs": [{"alias": null, "id": 709326, "history": [{"changes": [{"removed": "", "added": "fmdevelopertim@gmail.com", "field_name": "cc"}, {"removed": "General", "added": "about:memory", "field_name": "component"}, {"removed": "Firefox", "added": "Toolkit", "field_name": "product"}, {"field_name": "qa_contact", "added": "about.memory@toolkit.bugs", "removed": "general@firefox.bugs"}], "who": "fmdevelopertim@gmail.com", "when": "2011-12-10T00:22:50Z"}, {"changes": [{"added": "nnethercote@mozilla.com", "removed": "", "field_name": "cc"}], "who": "n.nethercote@gmail.com", "when": "2011-12-12T02:18:33Z"}, {"changes": [{"field_name": "summary", "added": "After private browsing has closed, sites viewed can still be visible in about:memory", "removed": "Private information disclosure"}], "when": "2011-12-12T23:35:35Z", "who": "n.nethercote@gmail.com"}, {"who": "justin.lebar+bug@gmail.com", "when": "2012-01-03T19:51:04Z", "changes": [{"added": "justin.lebar+bug@gmail.com", "removed": "", "field_name": "cc"}]}, {"changes": [{"added": "cam@mcc.id.au", "removed": "", "field_name": "cc"}], "when": "2012-01-22T10:07:16Z", "who": "n.nethercote@gmail.com"}, {"who": "xtc4uall@gmail.com", "when": "2012-01-22T11:31:40Z", "changes": [{"added": "xtc4uall@gmail.com", "removed": "", "field_name": "cc"}, {"field_name": "platform", "removed": "x86", "added": "All"}, {"field_name": "version", "removed": "8 Branch", "added": "Trunk"}, {"added": "All", "removed": "Mac OS X", "field_name": "op_sys"}]}, {"changes": [{"field_name": "blocks", "removed": "", "added": "724677"}], "when": "2012-02-14T22:29:18Z", "who": "justin.lebar+bug@gmail.com"}, {"when": "2012-02-14T22:30:23Z", "who": "justin.lebar+bug@gmail.com", "changes": [{"field_name": "whiteboard", "added": "[mentor=jlebar]", "removed": ""}]}, {"who": "dbcooper.nz@gmail.com", "when": "2012-02-14T22:31:33Z", "changes": [{"added": "dbcooper.nz@gmail.com", "removed": "", "field_name": "cc"}]}, {"changes": [{"field_name": "cc", "removed": "", "added": "anthony.s.hughes@gmail.com"}], "who": "u279076@disabled.tld", "when": "2012-03-12T21:39:22Z"}, {"changes": [{"added": "1", "removed": "0", "field_name": "attachments.isobsolete", "attachment_id": 605222}, {"field_name": "flagtypes.name", "removed": "", "added": "review?(justin.lebar+bug@gmail.com)", "attachment_id": 605554}, {"field_name": "status", "added": "ASSIGNED", "removed": "UNCONFIRMED"}, {"added": "anthony.s.hughes@gmail.com", "removed": "nobody@mozilla.org", "field_name": "assigned_to"}, {"field_name": "is_confirmed", "removed": "0", "added": "1"}], "who": "u279076@disabled.tld", "when": "2012-03-13T21:49:38Z"}, {"who": "justin.lebar+bug@gmail.com", "when": "2012-03-14T16:16:51Z", "changes": [{"field_name": "flagtypes.name", "removed": "review?(justin.lebar+bug@gmail.com)", "added": "review-", "attachment_id": 605554}]}, {"when": "2012-03-25T04:16:27Z", "who": "u279076@disabled.tld", "changes": [{"field_name": "attachments.isobsolete", "added": "1", "removed": "0", "attachment_id": 605554}, {"attachment_id": 609070, "added": "feedback?(justin.lebar+bug@gmail.com)", "removed": "", "field_name": "flagtypes.name"}]}, {"when": "2012-04-06T15:54:18Z", "who": "justin.lebar+bug@gmail.com", "changes": [{"attachment_id": 609070, "field_name": "flagtypes.name", "added": "", "removed": "feedback?(justin.lebar+bug@gmail.com)"}]}, {"who": "justin.lebar+bug@gmail.com", "when": "2012-04-12T17:29:27Z", "changes": [{"field_name": "cc", "added": "bzbarsky@mit.edu", "removed": ""}]}, {"changes": [{"removed": "", "added": "josh@joshmatthews.net", "field_name": "cc"}], "who": "josh@joshmatthews.net", "when": "2012-04-12T19:42:34Z"}, {"when": "2012-05-22T17:36:28Z", "who": "u279076@disabled.tld", "changes": [{"removed": "anthony.s.hughes@gmail.com", "added": "nobody@mozilla.org", "field_name": "assigned_to"}]}, {"who": "u279076@disabled.tld", "when": "2012-05-22T17:36:38Z", "changes": [{"field_name": "status", "added": "NEW", "removed": "ASSIGNED"}]}, {"changes": [{"attachment_id": 609070, "added": "1", "removed": "0", "field_name": "attachments.isobsolete"}, {"added": "feedback?(justin.lebar+bug@gmail.com)", "removed": "", "field_name": "flagtypes.name", "attachment_id": 641377}, {"field_name": "status", "added": "ASSIGNED", "removed": "NEW"}, {"removed": "nobody@mozilla.org", "added": "kwierso@gmail.com", "field_name": "assigned_to"}], "when": "2012-07-12T07:06:26Z", "who": "kwierso@gmail.com"}, {"changes": [{"attachment_id": 641377, "removed": "feedback?(justin.lebar+bug@gmail.com)", "added": "feedback-", "field_name": "flagtypes.name"}], "who": "josh@joshmatthews.net", "when": "2012-07-12T12:16:21Z"}, {"changes": [{"removed": "", "added": "continuation@gmail.com", "field_name": "cc"}], "when": "2012-07-13T13:56:21Z", "who": "continuation@gmail.com"}, {"changes": [{"added": "firefox@4nyj.co.uk", "removed": "", "field_name": "cc"}], "who": "nigelh747@gmail.com", "when": "2012-10-10T06:39:07Z"}, {"changes": [{"field_name": "cc", "added": "kwierso@gmail.com", "removed": ""}, {"field_name": "assigned_to", "removed": "kwierso@gmail.com", "added": "nobody@mozilla.org"}], "who": "kwierso@gmail.com", "when": "2013-03-07T20:24:51Z"}, {"who": "gavin.sharp@gmail.com", "when": "2013-03-25T14:41:35Z", "changes": [{"added": "kml@public-files.de", "removed": "", "field_name": "cc"}]}, {"who": "gavin.sharp@gmail.com", "when": "2013-03-25T14:41:55Z", "changes": [{"added": "gavin.sharp@gmail.com", "removed": "", "field_name": "cc"}]}, {"changes": [{"field_name": "cc", "added": "ehsan@mozilla.com", "removed": ""}], "who": "ehsan.akhgari@gmail.com", "when": "2013-04-04T02:55:06Z"}, {"changes": [{"field_name": "flagtypes.name", "removed": "", "added": "needinfo?(josh@joshmatthews.net)"}], "when": "2013-04-04T02:56:28Z", "who": "ehsan.akhgari@gmail.com"}, {"changes": [{"added": "", "removed": "needinfo?(josh@joshmatthews.net)", "field_name": "flagtypes.name"}], "when": "2013-04-04T04:56:51Z", "who": "josh@joshmatthews.net"}, {"who": "ehsan.akhgari@gmail.com", "when": "2013-04-26T17:21:55Z", "changes": [{"added": "needinfo?(josh@joshmatthews.net)", "removed": "", "field_name": "flagtypes.name"}]}, {"changes": [{"field_name": "flagtypes.name", "added": "", "removed": "needinfo?(josh@joshmatthews.net)"}], "when": "2013-04-26T17:41:43Z", "who": "josh@joshmatthews.net"}, {"who": "guijoselito@gmail.com", "when": "2013-06-15T14:31:13Z", "changes": [{"added": "guijoselito@gmail.com", "removed": "", "field_name": "cc"}]}, {"changes": [{"added": "andrew0from@gmail.com", "removed": "", "field_name": "cc"}], "when": "2013-07-15T20:09:37Z", "who": "andrew0from@gmail.com"}, {"changes": [{"field_name": "cc", "removed": "andrew0from@gmail.com", "added": ""}], "who": "andrew0from@gmail.com", "when": "2013-07-15T20:09:41Z"}, {"changes": [{"field_name": "cc", "removed": "", "added": "mhoye@mozilla.com"}, {"removed": "[mentor=jlebar]", "added": "[mentor needed]", "field_name": "whiteboard"}, {"added": "needinfo?(ehsan@mozilla.com)", "removed": "", "field_name": "flagtypes.name"}], "when": "2014-06-19T15:24:34Z", "who": "mhoye@mozilla.com"}, {"when": "2014-06-19T15:39:37Z", "who": "ehsan.akhgari@gmail.com", "changes": [{"added": "[mentor=ehsan][lang=c++]", "removed": "[mentor needed]", "field_name": "whiteboard"}, {"field_name": "flagtypes.name", "added": "", "removed": "needinfo?(ehsan@mozilla.com)"}]}, {"changes": [{"added": "[lang=c++]", "removed": "[mentor=ehsan][lang=c++]", "field_name": "whiteboard"}, {"added": "ehsan@mozilla.com", "removed": "", "field_name": "bug_mentor"}], "when": "2014-06-19T15:40:41Z", "who": "continuation@gmail.com"}, {"changes": [{"removed": "", "added": "harshil158@gmail.com", "field_name": "cc"}], "when": "2014-11-22T13:33:48Z", "who": "harshil158@gmail.com"}, {"changes": [{"field_name": "cc", "removed": "", "added": "nfroyd@mozilla.com"}], "when": "2015-01-06T02:29:28Z", "who": "froydnj+bz@gmail.com"}, {"who": "n.nethercote@gmail.com", "when": "2015-01-06T04:19:17Z", "changes": [{"removed": "", "added": "feedback?(bzbarsky@mit.edu)", "field_name": "flagtypes.name", "attachment_id": 8544356}]}, {"changes": [{"field_name": "assigned_to", "removed": "nobody@mozilla.org", "added": "n.nethercote@gmail.com"}], "when": "2015-01-06T04:19:25Z", "who": "n.nethercote@gmail.com"}, {"changes": [{"field_name": "flagtypes.name", "added": "feedback?(ehsan@mozilla.com)", "removed": "", "attachment_id": 8544873}], "who": "n.nethercote@gmail.com", "when": "2015-01-06T23:54:56Z"}, {"changes": [{"attachment_id": 8544356, "added": "1", "removed": "0", "field_name": "attachments.isobsolete"}, {"removed": "feedback?(bzbarsky@mit.edu)", "added": "", "field_name": "flagtypes.name", "attachment_id": 8544356}], "when": "2015-01-06T23:55:03Z", "who": "n.nethercote@gmail.com"}, {"who": "n.nethercote@gmail.com", "when": "2015-01-06T23:56:27Z", "changes": [{"field_name": "attachments.isobsolete", "removed": "0", "added": "1", "attachment_id": 641377}]}, {"who": "n.nethercote@gmail.com", "when": "2015-01-07T01:16:39Z", "changes": [{"attachment_id": 8544873, "field_name": "flagtypes.name", "removed": "feedback?(ehsan@mozilla.com)", "added": ""}]}, {"when": "2015-01-30T01:26:29Z", "who": "n.nethercote@gmail.com", "changes": [{"removed": "n.nethercote@gmail.com", "added": "nobody@mozilla.org", "field_name": "assigned_to"}]}, {"changes": [{"removed": "", "added": "nickbryda@gmx.us", "field_name": "cc"}], "who": "nickbryda@gmx.us", "when": "2015-08-15T04:18:55Z"}, {"who": "aishwarya.naidu95@gmail.com", "when": "2016-03-21T16:10:50Z", "changes": [{"added": "aishwarya.naidu95@gmail.com", "removed": "", "field_name": "cc"}]}, {"changes": [{"added": "ahmedelserafy2016@gmail.com", "removed": "", "field_name": "cc"}], "who": "ahmedelserafy2016@gmail.com", "when": "2017-08-16T11:52:37Z"}, {"when": "2017-08-16T12:18:12Z", "who": "mhoye@mozilla.com", "changes": [{"removed": "", "added": "spam", "comment_id": 12571191, "field_name": "comment_tag", "comment_count": 63}]}, {"who": "sledru@mozilla.com", "when": "2018-10-15T08:37:12Z", "changes": [{"added": "NEW", "removed": "ASSIGNED", "field_name": "status"}]}, {"changes": [{"removed": "", "added": "jrmma.madhu@gmail.com", "field_name": "cc"}], "when": "2018-10-22T08:11:24Z", "who": "jrmma.madhu@gmail.com"}, {"changes": [{"added": "samo.golez@outlook.com", "removed": "", "field_name": "cc"}, {"field_name": "flagtypes.name", "added": "needinfo?(nick_whittome@hotmail.com)", "removed": ""}], "when": "2020-05-01T06:27:26Z", "who": "samo.golez@outlook.com"}, {"changes": [{"added": "security@mozilla.org", "removed": "", "field_name": "cc"}], "who": "nigelh747@gmail.com", "when": "2020-05-08T04:38:57Z"}, {"when": "2020-05-08T13:27:07Z", "who": "gijskruitbosch+bugs@gmail.com", "changes": [{"removed": "security@mozilla.org", "added": "", "field_name": "cc"}]}, {"when": "2020-05-08T15:59:54Z", "who": "continuation@gmail.com", "changes": [{"added": "", "removed": "needinfo?(nick_whittome@hotmail.com)", "field_name": "flagtypes.name"}]}, {"who": "continuation@gmail.com", "when": "2020-05-09T02:25:46Z", "changes": [{"field_name": "comment_tag", "comment_id": 14805898, "removed": "", "added": "offtopic", "comment_count": 72}]}, {"who": "Andreas-GitHub@protonmail.com", "when": "2020-05-14T12:20:04Z", "changes": [{"field_name": "cc", "removed": "", "added": "Andreas-GitHub@protonmail.com"}]}, {"when": "2020-05-14T16:20:53Z", "who": "continuation@gmail.com", "changes": [{"comment_count": 73, "added": "metoo", "removed": "", "comment_id": 14819220, "field_name": "comment_tag"}]}, {"when": "2020-05-19T00:15:08Z", "who": "jack@pryne.com", "changes": [{"field_name": "cc", "added": "jack@pryne.com", "removed": ""}]}, {"who": "annygakhokidze@gmail.com", "when": "2021-03-04T21:47:33Z", "changes": [{"removed": "", "added": "agakhokidze@mozilla.com", "field_name": "cc"}]}, {"who": "continuation@gmail.com", "when": "2021-09-17T15:39:20Z", "changes": [{"field_name": "bug_mentor", "removed": "ehsan.akhgari@gmail.com", "added": ""}]}, {"changes": [{"removed": "josh@joshmatthews.net", "added": "", "field_name": "cc"}], "who": "josh@joshmatthews.net", "when": "2021-09-17T23:13:10Z"}]}]}