{"bugs": [{"alias": null, "id": 654005, "history": [{"when": "2011-05-01T18:04:50Z", "changes": [{"field_name": "cf_blocking_seamonkey21", "added": "?", "removed": "---"}], "who": "philip.chee@gmail.com"}, {"who": "jh@junetz.de", "changes": [{"removed": "", "field_name": "cc", "added": "jh@junetz.de"}], "when": "2011-05-01T18:33:56Z"}, {"who": "u331436@disabled.tld", "when": "2011-05-02T06:28:10Z", "changes": [{"removed": "", "added": "dominique@hp.com", "field_name": "cc"}]}, {"when": "2011-05-02T20:50:13Z", "changes": [{"removed": "", "added": "bugspam.Callek@gmail.com", "field_name": "cc"}, {"removed": "?", "field_name": "cf_blocking_seamonkey21", "added": "-"}], "who": "bugspam.Callek@gmail.com"}]}]}