{"bugs": {"708584": {"comments": [{"bug_id": 708584, "count": 0, "id": 5900229, "raw_text": "User Agent: Mozilla/5.0 (Macintosh; Intel Mac OS X 10_7_2) AppleWebKit/534.52.7 (KHTML, like Gecko) Version/5.1.2 Safari/534.52.7\n\nSteps to reproduce:\n\nTried to make a new browser window while viewing the source for a different page.\n\n\nActual results:\n\nNothing, the file menu didn't have a \"New Window\" entry.\n\n\nExpected results:\n\nThere should have been a \"New Window\" entry in the File Menu, and I should have been able to create a new window.", "attachment_id": 580001, "text": "Created attachment 580001\nnoNewWindowMenu.png\n\nUser Agent: Mozilla/5.0 (Macintosh; Intel Mac OS X 10_7_2) AppleWebKit/534.52.7 (KHTML, like Gecko) Version/5.1.2 Safari/534.52.7\n\nSteps to reproduce:\n\nTried to make a new browser window while viewing the source for a different page.\n\n\nActual results:\n\nNothing, the file menu didn't have a \"New Window\" entry.\n\n\nExpected results:\n\nThere should have been a \"New Window\" entry in the File Menu, and I should have been able to create a new window.", "time": "2011-12-08T12:27:35Z", "tags": [], "creation_time": "2011-12-08T12:27:35Z", "author": "marketers@me.com", "is_private": false, "creator": "marketers@me.com"}]}}, "comments": {}}