{"bugs": [{"history": [{"who": "timeless@bemail.org", "when": "2005-06-29T05:51:39Z", "changes": [{"removed": "0", "field_name": "attachments.isobsolete", "added": "1", "attachment_id": 187598}]}, {"who": "timeless@bemail.org", "when": "2005-06-29T07:00:03Z", "changes": [{"attachment_id": 187607, "added": "1", "field_name": "attachments.isobsolete", "removed": "0"}]}, {"who": "jaime.bugzilla@gmail.com", "when": "2005-06-29T13:06:33Z", "changes": [{"added": "bugzilla@jaimem.org.uk", "field_name": "cc", "removed": ""}]}, {"who": "ajschult784@gmail.com", "when": "2005-06-29T15:27:18Z", "changes": [{"field_name": "keywords", "added": "crash", "removed": ""}, {"added": "Trunk", "field_name": "version", "removed": "unspecified"}, {"removed": "Windows XP", "field_name": "op_sys", "added": "All"}, {"removed": "UNCONFIRMED", "added": "NEW", "field_name": "status"}, {"added": "critical", "field_name": "severity", "removed": "minor"}, {"removed": "0", "added": "1", "field_name": "is_confirmed"}]}, {"changes": [{"added": "299146", "field_name": "depends_on", "removed": ""}], "when": "2005-06-29T16:03:19Z", "who": "timeless@bemail.org"}, {"when": "2005-06-30T02:38:42Z", "who": "gavin.sharp@gmail.com", "changes": [{"added": "gavin.sharp@gmail.com", "field_name": "cc", "removed": ""}]}, {"who": "pavel.penaz@gmail.com", "when": "2005-07-02T20:33:40Z", "changes": [{"field_name": "cc", "added": "pavel.penaz@gmail.com", "removed": ""}]}, {"changes": [{"field_name": "cc", "added": "torisugari@gmail.com", "removed": ""}], "when": "2005-08-09T10:38:33Z", "who": "torisugari@gmail.com"}, {"when": "2005-11-27T03:31:05Z", "who": "ispiked@gmail.com", "changes": [{"field_name": "cc", "added": "ispiked@gmail.com", "removed": ""}]}, {"who": "ispiked@gmail.com", "when": "2005-11-27T03:39:39Z", "changes": [{"added": "Crash if addSearchEngine called with invalid search plugin file but valid search icon (mycroft search engine) [@ nsCharTraits::length]", "field_name": "summary", "removed": "Crash if addSearchEngine called with invalid search plugin file but valid search icon (mycroft search engine)"}, {"added": "RESOLVED", "field_name": "status", "removed": "NEW"}, {"removed": "", "added": "FIXED", "field_name": "resolution"}, {"removed": "", "added": "2005-11-27T03:39:39Z", "field_name": "cf_last_resolved"}]}, {"changes": [{"removed": "", "added": "[@ nsCharTraits::length]", "field_name": "cf_crash_signature"}], "who": "nobody@mozilla.org", "when": "2011-06-09T21:58:42Z"}], "alias": null, "id": 299090}]}