{"bugs": [{"history": [{"who": "bugzilla-mozilla-20000923@james-ross.co.uk", "when": "2011-03-07T13:22:49Z", "changes": [{"added": "silver@warwickcompsoc.co.uk", "field_name": "cc", "removed": ""}]}, {"who": "moz@vovo.id.au", "changes": [{"removed": "UNCONFIRMED", "added": "NEW", "field_name": "status"}, {"added": "David.Vo2+bmo@gmail.com", "field_name": "cc", "removed": ""}, {"removed": "x86_64", "field_name": "platform", "added": "All"}, {"field_name": "is_confirmed", "added": "1", "removed": "0"}, {"field_name": "op_sys", "added": "All", "removed": "Windows 7"}], "when": "2011-03-09T05:08:36Z"}, {"who": "honza.hron@post.cz", "when": "2012-12-26T22:58:12Z", "changes": [{"removed": "", "field_name": "cc", "added": "honza.hron@post.cz"}]}], "id": 639416, "alias": null}]}