{"comments": {}, "bugs": {"711351": {"comments": [{"creation_time": "2011-12-16T09:39:41Z", "author": "towo@towo.net", "text": "Bookmarks separators in SeaMonkey 2.0 (and Firefox 2.0) could have labels which are part of my bookmarks data that I want to maintain in new versions.\n\nThis nice feature was lost with 2.1 by integrating the terrible new bookmarks system of Firefox.\n\nFor a discussion of the issue, see Firefox bug https://bugzilla.mozilla.org/show_bug.cgi?id=121053\n\nSeverity: this leads to dataloss for the users, so I consider it critical. Also, it would be really easy to fix, another argument for \"critical\" for a bug that annoys so many power users.", "time": "2011-12-16T09:39:41Z", "tags": [], "is_private": false, "creator": "towo@towo.net", "id": 5921362, "attachment_id": null, "raw_text": "Bookmarks separators in SeaMonkey 2.0 (and Firefox 2.0) could have labels which are part of my bookmarks data that I want to maintain in new versions.\n\nThis nice feature was lost with 2.1 by integrating the terrible new bookmarks system of Firefox.\n\nFor a discussion of the issue, see Firefox bug https://bugzilla.mozilla.org/show_bug.cgi?id=121053\n\nSeverity: this leads to dataloss for the users, so I consider it critical. Also, it would be really easy to fix, another argument for \"critical\" for a bug that annoys so many power users.", "bug_id": 711351, "count": 0}, {"bug_id": 711351, "count": 1, "time": "2011-12-16T10:31:45Z", "tags": [], "text": "See Firefox Bug 404983 - Separators don't have names/descriptions any longer.", "author": "philip.chee@gmail.com", "creation_time": "2011-12-16T10:31:45Z", "creator": "philip.chee@gmail.com", "is_private": false, "id": 5921416, "raw_text": "See Firefox Bug 404983 - Separators don't have names/descriptions any longer.", "attachment_id": null}, {"bug_id": 711351, "count": 2, "id": 6657434, "attachment_id": null, "raw_text": "", "author": "pppx@i.com.ua", "creation_time": "2012-09-22T16:18:01Z", "tags": [], "time": "2012-09-22T16:18:01Z", "text": "*** Bug 208017 has been marked as a duplicate of this bug. ***", "creator": "pppx@i.com.ua", "is_private": false}]}}}