{"faults": [], "bugs": [{"creator": "ludo.aelbrecht+mozilla@gmail.com", "comment_count": 1, "depends_on": [], "priority": "--", "creator_detail": {"nick": "ludo.aelbrecht+mozilla", "name": "ludo.aelbrecht+mozilla@gmail.com", "email": "ludo.aelbrecht+mozilla@gmail.com", "real_name": "Ludovic", "id": 100489}, "cc": [], "is_cc_accessible": true, "keywords": [], "op_sys": "Windows 7", "cf_tracking_thunderbird_esr91": "---", "qa_contact": "", "is_open": true, "flags": [], "last_change_time": "2011-12-10T21:39:40Z", "dupe_of": null, "cf_status_thunderbird_98": "---", "assigned_to": "nobody@mozilla.org", "regressed_by": [], "cf_status_thunderbird_97": "---", "version": "Lightning 1.0", "whiteboard": "", "see_also": [], "alias": null, "assigned_to_detail": {"email": "nobody@mozilla.org", "real_name": "Nobody; OK to take it and work on it", "id": 1, "nick": "nobody", "name": "nobody@mozilla.org"}, "id": 709505, "cf_status_thunderbird_esr91": "---", "duplicates": [], "cf_user_story": "", "classification": "Client Software", "cf_fx_points": "---", "cf_tracking_thunderbird_96": "---", "regressions": [], "is_confirmed": false, "severity": "normal", "groups": [], "cf_last_resolved": null, "creation_time": "2011-12-10T21:39:40Z", "cf_crash_signature": "", "cf_tracking_thunderbird_98": "---", "votes": 0, "type": "enhancement", "status": "UNCONFIRMED", "target_milestone": "---", "resolution": "", "component": "Calendar Frontend", "mentors": [], "mentors_detail": [], "cf_fx_iteration": "---", "blocks": [], "cf_status_thunderbird_96": "---", "cf_qa_whiteboard": "", "platform": "x86", "summary": "In monthly view, add spacing between appointments depending on the time", "cf_tracking_thunderbird_97": "---", "cc_detail": [], "is_creator_accessible": true, "product": "Calendar", "url": ""}]}