{"comments": {}, "bugs": {"629629": {"comments": [{"tags": [], "creation_time": "2011-01-28T10:00:05Z", "is_private": false, "text": "User-Agent:       Mozilla/5.0 (Windows NT 6.1; rv:2.0b11pre) Gecko/20110127 Firefox/4.0b11pre\nBuild Identifier: Mozilla/5.0 (Windows NT 6.1; rv:2.0b11pre) Gecko/20110127 Firefox/4.0b11pre\n\nthe print toolbar need a translucent border as the content area\n\nReproducible: Always", "id": 5234851, "count": 0, "time": "2011-01-28T10:00:05Z", "creator": "valeriopetroni@hotmail.it", "attachment_id": null, "author": "valeriopetroni@hotmail.it", "bug_id": 629629, "raw_text": "User-Agent:       Mozilla/5.0 (Windows NT 6.1; rv:2.0b11pre) Gecko/20110127 Firefox/4.0b11pre\nBuild Identifier: Mozilla/5.0 (Windows NT 6.1; rv:2.0b11pre) Gecko/20110127 Firefox/4.0b11pre\n\nthe print toolbar need a translucent border as the content area\n\nReproducible: Always"}, {"creator": "valeriopetroni@hotmail.it", "attachment_id": 507812, "author": "valeriopetroni@hotmail.it", "time": "2011-01-28T10:10:44Z", "tags": [], "creation_time": "2011-01-28T10:10:44Z", "count": 1, "raw_text": "giving to the print toolbar the same appearance of the other toolbars it's possible to create around it the same translucent border. I made this with:\n\n#print-preview-toolbar:not(:-moz-lwtheme)  {\n    -moz-appearance: none !important;\n    border-top: 1px solid rgba(10%,10%,10%,.4) !important;\n    border-bottom: 1px solid rgba(10%,10%,10%,.4) !important;\n    background: hsl(214,44%,87%) padding-box !important;\n    background-image: -moz-linear-gradient(rgba(255,255,255,.5), rgba(255,255,255,0)) !important; \n  }\n\n  #main-window[sizemode=\"normal\"] #print-preview-toolbar:not(:-moz-lwtheme)  {\n    border: 1px solid rgba(10%,10%,10%,.4) !important;\n    border-radius: 3.5px 3.5px 0 0 !important;\n  }", "id": 5234864, "is_private": false, "bug_id": 629629, "text": "Created attachment 507812\nPrint toolbar before and after\n\ngiving to the print toolbar the same appearance of the other toolbars it's possible to create around it the same translucent border. I made this with:\n\n#print-preview-toolbar:not(:-moz-lwtheme)  {\n    -moz-appearance: none !important;\n    border-top: 1px solid rgba(10%,10%,10%,.4) !important;\n    border-bottom: 1px solid rgba(10%,10%,10%,.4) !important;\n    background: hsl(214,44%,87%) padding-box !important;\n    background-image: -moz-linear-gradient(rgba(255,255,255,.5), rgba(255,255,255,0)) !important; \n  }\n\n  #main-window[sizemode=\"normal\"] #print-preview-toolbar:not(:-moz-lwtheme)  {\n    border: 1px solid rgba(10%,10%,10%,.4) !important;\n    border-radius: 3.5px 3.5px 0 0 !important;\n  }"}, {"is_private": false, "text": "Buttons need to be updated as well.", "bug_id": 629629, "raw_text": "Buttons need to be updated as well.", "count": 2, "id": 5251209, "time": "2011-02-03T12:31:47Z", "creator": "terepin64@gmail.com", "attachment_id": null, "author": "terepin64@gmail.com", "tags": [], "creation_time": "2011-02-03T12:31:47Z"}, {"bug_id": 629629, "raw_text": "Any activity here? This Fx 3.x design is very outdated. It's the same old design like you'll find in the error console and a rework is overdue.", "time": "2012-01-23T20:14:07Z", "creator": "dragi86@gmail.com", "author": "dragi86@gmail.com", "attachment_id": null, "is_private": false, "text": "Any activity here? This Fx 3.x design is very outdated. It's the same old design like you'll find in the error console and a rework is overdue.", "id": 6001759, "count": 3, "tags": [], "creation_time": "2012-01-23T20:14:07Z"}]}}}