{"bugs": [{"id": 696120, "alias": null, "history": [{"changes": [{"added": "x86_64", "field_name": "platform", "removed": "x86"}, {"added": "Mac OS X", "field_name": "op_sys", "removed": "Windows 7"}], "who": "sergey.belsky@gmail.com", "when": "2011-10-20T16:43:04Z"}, {"changes": [{"removed": "", "added": "matti@mversen.de", "field_name": "cc"}], "when": "2011-10-20T17:25:24Z", "who": "bugzilla@mversen.de"}, {"when": "2012-07-17T16:58:17Z", "who": "bugzillawatcher@gmail.com", "changes": [{"field_name": "cc", "added": "bugzillawatcher@gmail.com", "removed": ""}]}]}]}