{"faults": [], "bugs": [{"severity": "normal", "resolution": "", "qa_contact": "", "blocks": [], "status": "NEW", "votes": 0, "alias": null, "cc": ["ck@christi3k.net"], "regressed_by": [], "depends_on": [], "priority": "--", "comment_count": 1, "creator_detail": {"nick": "k0scist", "id": 376043, "real_name": "Jeff Hammel", "name": "k0scist@gmail.com", "email": "k0scist@gmail.com"}, "last_change_time": "2014-07-27T14:54:38Z", "classification": "Other", "product": "Websites", "dupe_of": null, "target_milestone": "---", "is_cc_accessible": true, "cf_fx_points": "---", "regressions": [], "cf_qa_whiteboard": "", "mentors": [], "platform": "All", "duplicates": [], "flags": [], "creation_time": "2011-04-25T18:12:43Z", "cf_fx_iteration": "---", "mentors_detail": [], "op_sys": "All", "is_confirmed": true, "is_open": true, "assigned_to": "nobody@mozilla.org", "see_also": [], "version": "unspecified", "cc_detail": [{"nick": "ckoehler", "name": "ck@christi3k.net", "email": "ck@christi3k.net", "real_name": "Christie Koehler [:ckoehler]", "id": 425073}], "groups": [], "is_creator_accessible": true, "id": 652582, "cf_user_story": "", "keywords": [], "creator": "k0scist@gmail.com", "whiteboard": "[featurerequest]", "component": "wiki.mozilla.org", "summary": "Wiki pages from templates + \"cron\" jobs", "url": "", "cf_last_resolved": null, "assigned_to_detail": {"nick": "nobody", "id": 1, "real_name": "Nobody; OK to take it and work on it", "name": "nobody@mozilla.org", "email": "nobody@mozilla.org"}, "type": "enhancement"}]}