{"bugs": [{"last_change_time": "2019-05-19T09:33:17Z", "cf_status_seamonkey253": "---", "classification": "Components", "mentors_detail": [], "platform": "All", "groups": [], "creation_time": "2011-10-25T19:58:49Z", "regressions": [], "version": "unspecified", "regressed_by": [], "alias": null, "cc": ["vseerror@lehigh.edu"], "creator_detail": {"id": 11539, "nick": "jesup", "real_name": "Randell Jesup [:jesup] (needinfo me)", "name": "rjesup@jesup.org", "email": "rjesup@jesup.org"}, "cf_tracking_thunderbird_98": "---", "component": "Composition", "keywords": [], "severity": "normal", "cf_fx_iteration": "---", "dupe_of": null, "is_cc_accessible": true, "cf_tracking_thunderbird_esr91": "---", "id": 697231, "cf_user_story": "", "cf_status_thunderbird_96": "---", "cf_qa_whiteboard": "", "creator": "rjesup@jesup.org", "priority": "--", "mentors": [], "see_also": ["https://bugzilla.mozilla.org/show_bug.cgi?id=691115"], "is_creator_accessible": true, "cf_fx_points": "---", "cc_detail": [{"id": 29811, "nick": "wsmwk", "real_name": "Wayne Mery (:wsmwk)", "name": "vseerror@lehigh.edu", "email": "vseerror@lehigh.edu"}], "type": "defect", "cf_status_thunderbird_esr91": "---", "duplicates": [], "votes": 0, "resolution": "", "is_open": true, "cf_tracking_thunderbird_96": "---", "cf_crash_signature": "", "blocks": [], "cf_status_seamonkey257esr": "---", "cf_status_thunderbird_98": "---", "cf_status_thunderbird_97": "---", "flags": [], "is_confirmed": true, "op_sys": "All", "comment_count": 1, "cf_tracking_seamonkey253": "---", "assigned_to_detail": {"email": "nobody@mozilla.org", "name": "nobody@mozilla.org", "real_name": "Nobody; OK to take it and work on it", "id": 1, "nick": "nobody"}, "summary": "hand-wrapping quoted text when in text mode (shift-reply) causes mix of \"change bars\" and '>'s", "cf_last_resolved": null, "status": "NEW", "cf_tracking_seamonkey257esr": "---", "cf_tracking_thunderbird_97": "---", "qa_contact": "", "assigned_to": "nobody@mozilla.org", "cf_tracking_firefox_sumo": "---", "cf_tracking_firefox_relnote": "---", "depends_on": [], "product": "MailNews Core", "target_milestone": "---", "whiteboard": "", "url": ""}], "faults": []}