{"bugs": [{"cf_fx_iteration": "---", "whiteboard": "", "creator_detail": {"name": "john728@charter.net", "id": 365458, "email": "john728@charter.net", "nick": "john728", "real_name": "John"}, "cf_status_thunderbird_96": "---", "duplicates": [], "is_open": true, "cf_fx_points": "---", "cf_tracking_thunderbird_esr91": "---", "mentors": [], "cf_status_thunderbird_98": "---", "cf_last_resolved": "2011-01-28T03:09:51Z", "see_also": [], "cf_qa_whiteboard": "", "cf_tracking_thunderbird_98": "---", "cf_crash_signature": "", "summary": "Save multiple messages at once as text or HTML files", "cc_detail": [{"real_name": "Joshua Cranmer [:jcranmer]", "name": "Pidgeot18@gmail.com", "email": "Pidgeot18@gmail.com", "nick": "jcranmer", "id": 286107}], "votes": 0, "alias": null, "regressions": [], "cf_user_story": "", "flags": [], "url": "", "groups": [], "dupe_of": null, "is_creator_accessible": true, "target_milestone": "---", "blocks": [], "comment_count": 6, "status": "UNCONFIRMED", "creation_time": "2011-01-28T02:21:19Z", "cf_status_thunderbird_97": "---", "product": "Thunderbird", "creator": "john728@charter.net", "last_change_time": "2016-07-06T15:31:36Z", "mentors_detail": [], "qa_contact": "", "classification": "Client Software", "depends_on": [], "severity": "normal", "type": "enhancement", "platform": "x86", "priority": "--", "cf_tracking_thunderbird_96": "---", "assigned_to_detail": {"real_name": "Nobody; OK to take it and work on it", "id": 1, "nick": "nobody", "email": "nobody@mozilla.org", "name": "nobody@mozilla.org"}, "regressed_by": [], "is_cc_accessible": true, "assigned_to": "nobody@mozilla.org", "cc": ["Pidgeot18@gmail.com"], "keywords": [], "component": "General", "id": 629580, "resolution": "", "version": "unspecified", "cf_tracking_thunderbird_97": "---", "is_confirmed": false, "op_sys": "Windows XP", "cf_status_thunderbird_esr91": "---"}], "faults": []}