{"bugs": [{"id": 624104, "history": [{"who": "ehsan.akhgari@gmail.com", "changes": [{"removed": "", "added": "ehsan@mozilla.com", "field_name": "cc"}], "when": "2011-01-08T06:51:47Z"}, {"who": "bzbarsky@mit.edu", "when": "2011-01-09T01:44:52Z", "changes": [{"field_name": "cc", "added": "cbiesinger@gmail.com, dmose@mozilla.org, jonas@sicking.cc", "removed": ""}]}, {"who": "ph@patrickhubenthal.com", "changes": [{"removed": "", "added": "kronpilz@yahoo.com", "field_name": "cc"}], "when": "2017-10-27T18:25:34Z"}, {"changes": [{"removed": "jonas@sicking.cc", "added": "", "field_name": "cc"}], "when": "2017-10-27T21:39:46Z", "who": "jonas@sicking.cc"}, {"who": "dmosedale@mozilla.com", "changes": [{"field_name": "cc", "added": "", "removed": "dmose@mozilla.org"}], "when": "2017-10-30T18:05:15Z"}, {"who": "cbiesinger@gmail.com", "changes": [{"removed": "cbiesinger@gmail.com", "field_name": "cc", "added": ""}], "when": "2017-11-01T22:52:25Z"}, {"when": "2017-11-24T13:47:49Z", "changes": [{"removed": "", "field_name": "see_also", "added": "https://bugzilla.mozilla.org/show_bug.cgi?id=499527"}], "who": "standard8@mozilla.com"}], "alias": null}]}