{"faults": [], "bugs": [{"cf_crash_signature": "", "mentors_detail": [], "cf_tracking_firefox_sumo": "---", "summary": "Allow configuring server side filters (Zimbra)", "cf_tracking_seamonkey257esr": "---", "cf_fx_iteration": "---", "assigned_to": "nobody@mozilla.org", "cf_tracking_firefox_relnote": "---", "dupe_of": null, "cf_tracking_thunderbird_97": "---", "is_open": true, "component": "Filters", "whiteboard": "", "creation_time": "2011-11-30T19:40:04Z", "classification": "Components", "target_milestone": "---", "version": "Trunk", "cf_status_thunderbird_97": "---", "product": "MailNews Core", "assigned_to_detail": {"id": 1, "name": "nobody@mozilla.org", "nick": "nobody", "email": "nobody@mozilla.org", "real_name": "Nobody; OK to take it and work on it"}, "is_cc_accessible": true, "cf_status_seamonkey253": "---", "cc": ["bugmail@asutherland.org", "justdave@bugzilla.org", "mkmelin+mozilla@iki.fi", "Pablo.Iranzo@redhat.com", "reed@reedloden.com", "vseerror@lehigh.edu"], "is_creator_accessible": true, "cf_status_thunderbird_96": "---", "comment_count": 5, "last_change_time": "2015-09-30T13:26:22Z", "regressions": [], "is_confirmed": true, "cf_fx_points": "---", "url": "", "platform": "x86_64", "keywords": [], "cf_status_seamonkey257esr": "---", "creator_detail": {"id": 8558, "email": "hub@figuiere.net", "nick": "hub", "real_name": "Hubert Figuiere [:hub]", "name": "hub@figuiere.net"}, "resolution": "", "severity": "normal", "duplicates": [], "cf_tracking_seamonkey253": "---", "cf_status_thunderbird_98": "---", "creator": "hub@figuiere.net", "regressed_by": [], "see_also": [], "priority": "--", "depends_on": [79525], "status": "NEW", "cf_tracking_thunderbird_esr91": "---", "cf_last_resolved": null, "alias": null, "flags": [], "qa_contact": "", "cf_status_thunderbird_esr91": "---", "cc_detail": [{"id": 151407, "nick": "asuth", "real_name": "Andrew Sutherland [:asuth] (he/him)", "email": "bugmail@asutherland.org", "name": "bugmail@asutherland.org"}, {"id": 10297, "email": "justdave@bugzilla.org", "real_name": "Dave Miller [:justdave]", "nick": "justdave", "name": "justdave@bugzilla.org"}, {"name": "mkmelin+mozilla@iki.fi", "nick": "mkmelin", "email": "mkmelin+mozilla@iki.fi", "real_name": "Magnus Melin [:mkmelin]", "id": 101158}, {"id": 358783, "real_name": "Pablo Iranzo Gomez", "email": "Pablo.Iranzo@redhat.com", "nick": "Pablo.Iranzo", "name": "Pablo.Iranzo@redhat.com"}, {"id": 159758, "real_name": "Reed Loden [:reed]", "email": "reed@reedloden.com", "nick": "reed", "name": "reed@reedloden.com"}, {"name": "vseerror@lehigh.edu", "real_name": "Wayne Mery (:wsmwk)", "nick": "wsmwk", "email": "vseerror@lehigh.edu", "id": 29811}], "op_sys": "All", "cf_qa_whiteboard": "", "cf_user_story": "", "groups": [], "type": "enhancement", "cf_tracking_thunderbird_98": "---", "mentors": [], "cf_tracking_thunderbird_96": "---", "blocks": [], "votes": 0, "id": 706589}]}