{"bugs": [{"alias": null, "id": 639196, "history": [{"who": "iannbugzilla@gmail.com", "when": "2011-03-05T20:24:50Z", "changes": [{"field_name": "flagtypes.name", "added": "review?(neil@httl.net)", "removed": "", "attachment_id": 517165}]}, {"who": "u331436@disabled.tld", "when": "2011-03-06T08:35:10Z", "changes": [{"field_name": "cc", "added": "dominique@hp.com", "removed": ""}]}, {"who": "neil@httl.net", "changes": [{"field_name": "flagtypes.name", "attachment_id": 517165, "added": "feedback?(mnyromyr@tprac.de)", "removed": ""}], "when": "2011-03-19T00:49:40Z"}, {"when": "2011-03-26T21:27:11Z", "changes": [{"field_name": "flagtypes.name", "removed": "feedback?(mnyromyr@tprac.de)", "attachment_id": 517165, "added": "feedback-"}], "who": "mnyromyr@tprac.de"}, {"who": "neil@httl.net", "changes": [{"added": "review-", "removed": "review?(neil@httl.net)", "attachment_id": 517165, "field_name": "flagtypes.name"}], "when": "2011-03-26T23:23:12Z"}]}]}