{"bugs": [{"alias": null, "id": 672919, "history": [{"changes": [{"removed": "Upper subjects window is not scrolling to first unread message in newsgroups", "field_name": "summary", "added": "[View>Threads>Unread] Message list is not scrolling to first unread message in newsgroups"}, {"field_name": "version", "removed": "5.0", "added": "Trunk"}, {"field_name": "status", "removed": "UNCONFIRMED", "added": "NEW"}, {"removed": "", "field_name": "cc", "added": "bmo2010@ilias.ca"}, {"added": "1", "removed": "0", "field_name": "is_confirmed"}], "who": "bmo2018@ilias.ca", "when": "2011-08-03T21:40:51Z"}, {"changes": [{"added": "bachastain@sbcglobal.net", "field_name": "cc", "removed": ""}], "who": "bachastain@sbcglobal.net", "when": "2011-08-03T21:56:08Z"}, {"who": "vseerror@lehigh.edu", "changes": [{"removed": "", "field_name": "cc", "added": "vseerror@lehigh.edu, wls220spring@gmail.com"}, {"added": "All", "field_name": "op_sys", "removed": "Other"}, {"removed": "", "field_name": "flagtypes.name", "added": "needinfo?(wls220spring@gmail.com)"}], "when": "2021-10-23T13:19:06Z"}, {"who": "bmo2018@ilias.ca", "changes": [{"field_name": "cc", "removed": "bmo2018@ilias.ca", "added": ""}], "when": "2021-10-23T15:00:59Z"}, {"changes": [{"field_name": "flagtypes.name", "removed": "needinfo?(wls220spring@gmail.com)", "added": ""}], "who": "wls220spring@gmail.com", "when": "2021-10-26T17:20:33Z"}]}]}