{"bugs": [{"history": [{"when": "2011-10-17T22:51:00Z", "who": "bill.mccloskey@gmail.com", "changes": [{"field_name": "flagtypes.name", "attachment_id": 567609, "removed": "", "added": "review?(igor@mir2.org)"}]}, {"when": "2011-10-17T23:44:42Z", "who": "mail@lukewagner.name", "changes": [{"field_name": "cc", "removed": "", "added": "luke@mozilla.com"}]}, {"who": "matjk7@gmail.com", "changes": [{"removed": "", "field_name": "cc", "added": "matjk7@gmail.com"}], "when": "2011-10-18T03:22:21Z"}, {"changes": [{"attachment_id": 567609, "field_name": "flagtypes.name", "removed": "review?(igor@mir2.org)", "added": ""}], "who": "bill.mccloskey@gmail.com", "when": "2011-10-18T17:15:52Z"}, {"when": "2011-11-02T18:43:23Z", "changes": [{"added": "terrence@mozilla.com", "removed": "", "field_name": "cc"}], "who": "terrence.d.cole@gmail.com"}, {"who": "nobody@mozilla.org", "changes": [{"field_name": "assigned_to", "removed": "general@js.bugs", "added": "nobody@mozilla.org"}], "when": "2014-07-24T18:07:35Z"}], "id": 695212, "alias": null}]}