{"bugs": [{"id": 669045, "history": [{"changes": [{"added": "matjk7@gmail.com", "field_name": "cc", "removed": ""}], "when": "2011-07-03T06:11:08Z", "who": "matjk7@gmail.com"}, {"who": "xtc4uall@gmail.com", "when": "2011-07-03T15:57:56Z", "changes": [{"field_name": "cc", "added": "xtc4uall@gmail.com", "removed": ""}]}, {"changes": [{"removed": "x86_64", "field_name": "platform", "added": "All"}, {"removed": "Mac OS X", "field_name": "op_sys", "added": "All"}], "when": "2011-07-22T01:13:06Z", "who": "mounir@lamouri.fr"}, {"when": "2011-07-22T01:15:08Z", "changes": [{"removed": "testcase-wanted", "added": "testcase", "field_name": "keywords"}], "who": "mounir@lamouri.fr"}, {"who": "mounir@lamouri.fr", "when": "2011-07-22T01:58:01Z", "changes": [{"field_name": "platform", "added": "x86_64", "removed": "All"}, {"removed": "All", "field_name": "op_sys", "added": "Mac OS X"}]}, {"who": "mounir@lamouri.fr", "changes": [{"removed": "x86_64", "field_name": "platform", "added": "All"}, {"field_name": "op_sys", "added": "All", "removed": "Mac OS X"}], "when": "2011-07-22T01:58:19Z"}, {"who": "mounir@lamouri.fr", "when": "2011-08-01T06:34:45Z", "changes": [{"field_name": "blocks", "added": "445845", "removed": ""}]}, {"when": "2011-08-01T07:02:58Z", "changes": [{"field_name": "depends_on", "added": "675574", "removed": ""}], "who": "mounir@lamouri.fr"}, {"who": "djcater+bugzilla@gmail.com", "changes": [{"removed": "", "field_name": "cc", "added": "djcater+bugzilla@gmail.com"}], "when": "2011-09-10T21:12:41Z"}, {"who": "mounir@lamouri.fr", "when": "2011-09-28T21:51:49Z", "changes": [{"removed": "", "added": "[should be fixed by bug 675574]", "field_name": "whiteboard"}, {"added": "in-testsuite?", "field_name": "flagtypes.name", "removed": ""}]}, {"who": "BijuMailList@GMail.Com", "changes": [{"removed": "", "added": "BijuMailList@GMail.Com", "field_name": "cc"}], "when": "2012-04-25T05:04:59Z"}, {"who": "froydnj+bz@gmail.com", "when": "2014-09-02T14:13:29Z", "changes": [{"removed": "", "added": "nfroyd@mozilla.com", "field_name": "cc"}]}, {"when": "2014-09-02T15:40:34Z", "changes": [{"field_name": "cc", "added": "ehsan.akhgari@gmail.com", "removed": ""}], "who": "ehsan.akhgari@gmail.com"}, {"changes": [{"field_name": "priority", "added": "P5", "removed": "--"}], "when": "2018-06-29T04:49:47Z", "who": "bug-husbandry-bot@mozilla.bugs"}, {"when": "2019-03-13T13:42:05Z", "changes": [{"removed": "DOM", "added": "DOM: Core & HTML", "field_name": "component"}], "who": "nobody@mozilla.org"}], "alias": null}]}