{"bugs": [{"id": 320656, "alias": null, "history": [{"changes": [{"field_name": "summary", "added": "Link from iTunes email generates \"Item is not a registered protocol\"", "removed": "Link from iTune email generates \"Item is not a registered protocal\""}, {"removed": "General", "added": "OS Integration", "field_name": "component"}, {"removed": "general@firefox.bugs", "added": "os.integration@firefox.bugs", "field_name": "qa_contact"}, {"removed": "", "field_name": "cc", "added": "reed@reedloden.com"}], "who": "reed@reedloden.com", "when": "2005-12-17T21:52:33Z"}, {"when": "2005-12-19T00:10:50Z", "who": "mconnor@mozilla.com", "changes": [{"removed": "UNCONFIRMED", "added": "RESOLVED", "field_name": "status"}, {"removed": "", "added": "INVALID", "field_name": "resolution"}, {"added": "2005-12-19T00:10:50Z", "field_name": "cf_last_resolved", "removed": ""}]}]}]}