{"bugs": [{"regressed_by": [], "cf_qa_whiteboard": "", "mentors": [], "cf_fx_iteration": "---", "creation_time": "2020-05-06T13:07:49Z", "depends_on": [], "op_sys": "Unspecified", "version": "unspecified", "cf_status_firefox95": "---", "classification": "Client Software", "creator": "tlong@mozilla.com", "severity": "--", "regressions": [], "votes": 0, "url": "", "cf_user_story": "", "creator_detail": {"nick": "travis_", "real_name": "Travis Long [:travis_]", "id": 628857, "email": "tlong@mozilla.com", "name": "tlong@mozilla.com"}, "cc_detail": [{"real_name": "Chris H-C :chutten|PTO (back Jan 4)", "id": 553004, "nick": "chutten|PTO", "name": "chutten@mozilla.com", "email": "chutten@mozilla.com"}, {"real_name": "Jan-Erik Rediger [:janerik]  (PTO - back 2022-01-03)", "nick": "janerik", "id": 533624, "name": "jrediger@mozilla.com", "email": "jrediger@mozilla.com"}], "summary": "glean_parser allows underscores in the `send_in_pings` field.", "cf_last_resolved": "2020-05-12T13:15:14Z", "comment_count": 4, "status": "RESOLVED", "cf_status_firefox96": "---", "mentors_detail": [], "keywords": [], "cf_fx_points": "---", "blocks": [1637233], "cf_tracking_firefox97": "---", "assigned_to": "jrediger@mozilla.com", "component": "Glean: SDK", "cf_crash_signature": "", "see_also": [], "is_open": false, "cf_status_firefox97": "---", "cf_tracking_firefox95": "---", "target_milestone": "---", "is_creator_accessible": true, "dupe_of": null, "duplicates": [], "qa_contact": "", "priority": "P1", "is_confirmed": true, "whiteboard": "", "last_change_time": "2020-05-12T13:19:33Z", "cf_status_firefox_esr91": "---", "platform": "Unspecified", "cc": ["chutten@mozilla.com", "jrediger@mozilla.com"], "is_cc_accessible": true, "assigned_to_detail": {"id": 533624, "nick": "janerik", "real_name": "Jan-Erik Rediger [:janerik]  (PTO - back 2022-01-03)", "email": "jrediger@mozilla.com", "name": "jrediger@mozilla.com"}, "cf_tracking_firefox96": "---", "flags": [], "type": "defect", "id": 1635754, "alias": null, "resolution": "FIXED", "cf_tracking_firefox_esr91": "---", "product": "Data Platform and Tools", "groups": []}], "faults": []}