{"bugs": [{"history": [{"changes": [{"added": "smichaud@pobox.com", "removed": "", "field_name": "cc"}], "who": "enndeakin@gmail.com", "when": "2011-08-29T15:20:34Z"}, {"changes": [{"added": "gavin.sharp@gmail.com", "removed": "", "field_name": "cc"}], "when": "2011-08-31T21:40:48Z", "who": "gavin.sharp@gmail.com"}, {"when": "2013-07-16T02:21:51Z", "who": "markh@mozilla.com", "changes": [{"field_name": "cc", "added": "mhammond@mozilla.com", "removed": ""}]}, {"who": "bug-husbandry-bot@mozilla.bugs", "when": "2018-04-30T20:11:51Z", "changes": [{"removed": "XP Toolkit/Widgets: XUL", "added": "XUL", "field_name": "component"}]}], "id": 682732, "alias": null}]}