{"bugs": {"623206": {"comments": [{"creator": "bugzillamozillaorg_serge_20140323@gautherie.fr", "creation_time": "2011-01-05T14:45:21Z", "is_private": false, "id": 5176821, "text": "http://tinderbox.mozilla.org/showlog.cgi?log=MozillaTry/1294232561.1294233280.28251.gz\nRev3 Fedora 12 tryserver opt test mochitests-1/5 on 2011/01/05 05:02:41\n{\n28003 ERROR TEST-UNEXPECTED-FAIL | SimpleTest._logResult() | Next log line was cut because its length was too long (61546 > 16384): fix the test!\n28004 INFO TEST-PASS | /tests/content/base/test/test_fileapi.html | result in test plain reading - \"abcdef 123456\\nabcde [...]\n\n...\n\n28145 ERROR TEST-UNEXPECTED-FAIL | SimpleTest._logResult() | Next log line was cut because its length was too long (87574 > 16384): fix the test!\n28146 INFO TEST-PASS | /tests/content/base/test/test_fileapi.html | result in test reused reading data url - \"data:application/octet-stream;base64,AAECAwQFBgcICQo [...]\n}", "time": "2011-01-05T14:45:21Z", "tags": [], "author": "bugzillamozillaorg_serge_20140323@gautherie.fr", "attachment_id": null, "bug_id": 623206, "raw_text": "http://tinderbox.mozilla.org/showlog.cgi?log=MozillaTry/1294232561.1294233280.28251.gz\nRev3 Fedora 12 tryserver opt test mochitests-1/5 on 2011/01/05 05:02:41\n{\n28003 ERROR TEST-UNEXPECTED-FAIL | SimpleTest._logResult() | Next log line was cut because its length was too long (61546 > 16384): fix the test!\n28004 INFO TEST-PASS | /tests/content/base/test/test_fileapi.html | result in test plain reading - \"abcdef 123456\\nabcde [...]\n\n...\n\n28145 ERROR TEST-UNEXPECTED-FAIL | SimpleTest._logResult() | Next log line was cut because its length was too long (87574 > 16384): fix the test!\n28146 INFO TEST-PASS | /tests/content/base/test/test_fileapi.html | result in test reused reading data url - \"data:application/octet-stream;base64,AAECAwQFBgcICQo [...]\n}", "count": 0}, {"creator": "bug-husbandry-bot@mozilla.bugs", "creation_time": "2018-06-29T04:49:29Z", "is_private": false, "time": "2018-06-29T04:49:29Z", "text": "https://bugzilla.mozilla.org/show_bug.cgi?id=1472046\n\nMove all DOM bugs that haven\u2019t been updated in more than 3 years and has no one currently assigned to P5.\n\nIf you have questions, please contact :mdaly.", "id": 13436228, "author": "bug-husbandry-bot@mozilla.bugs", "tags": [], "bug_id": 623206, "attachment_id": null, "raw_text": "https://bugzilla.mozilla.org/show_bug.cgi?id=1472046\n\nMove all DOM bugs that haven\u2019t been updated in more than 3 years and has no one currently assigned to P5.\n\nIf you have questions, please contact :mdaly.", "count": 1}, {"is_private": false, "id": 13684886, "text": "No assignee, updating the status.", "time": "2018-10-15T08:32:56Z", "creator": "sledru@mozilla.com", "creation_time": "2018-10-15T08:32:56Z", "raw_text": "No assignee, updating the status.", "count": 2, "tags": [], "author": "sledru@mozilla.com", "attachment_id": null, "bug_id": 623206}, {"is_private": false, "time": "2018-10-15T08:35:11Z", "id": 13685038, "text": "No assignee, updating the status.", "creation_time": "2018-10-15T08:35:11Z", "creator": "sledru@mozilla.com", "count": 3, "raw_text": "No assignee, updating the status.", "bug_id": 623206, "attachment_id": null, "author": "sledru@mozilla.com", "tags": []}, {"raw_text": "No assignee, updating the status.", "count": 4, "tags": [], "author": "sledru@mozilla.com", "attachment_id": null, "bug_id": 623206, "text": "No assignee, updating the status.", "id": 13685350, "time": "2018-10-15T08:39:30Z", "is_private": false, "creator": "sledru@mozilla.com", "creation_time": "2018-10-15T08:39:30Z"}, {"raw_text": "No assignee, updating the status.", "count": 5, "tags": [], "author": "sledru@mozilla.com", "attachment_id": null, "bug_id": 623206, "text": "No assignee, updating the status.", "id": 13685599, "time": "2018-10-15T08:42:06Z", "is_private": false, "creator": "sledru@mozilla.com", "creation_time": "2018-10-15T08:42:06Z"}]}}, "comments": {}}