{"bugs": [{"alias": null, "history": [{"when": "2011-03-18T13:27:20Z", "who": "standard8@mozilla.com", "changes": [{"field_name": "summary", "removed": "RFE: A gender (sex) field for contact in address book", "added": "A gender (sex) field for contact in address book"}]}, {"changes": [{"added": "RESOLVED", "removed": "NEW", "field_name": "status"}, {"added": "ulysse@email.it", "field_name": "cc", "removed": ""}, {"added": "DUPLICATE", "removed": "", "field_name": "resolution"}, {"added": "2011-03-26T10:00:09Z", "field_name": "cf_last_resolved", "removed": ""}], "who": "euryalus.0@gmail.com", "when": "2011-03-26T10:00:09Z"}, {"when": "2011-03-28T14:23:13Z", "who": "lapsap7+mz@gmail.com", "changes": [{"removed": "RESOLVED", "field_name": "status", "added": "REOPENED"}, {"added": "", "field_name": "resolution", "removed": "DUPLICATE"}]}, {"changes": [{"removed": "", "field_name": "depends_on", "added": "266891"}], "who": "lapsap7+mz@gmail.com", "when": "2011-03-28T14:23:59Z"}, {"when": "2011-07-22T21:26:40Z", "who": "dasch@daschmedia.de", "changes": [{"field_name": "cc", "removed": "", "added": "dasch@daschmedia.de"}]}, {"when": "2011-08-26T08:22:12Z", "who": "thomas.bugzilla@lt-mail.com", "changes": [{"removed": "", "field_name": "cc", "added": "intrinsor@web.de"}]}, {"changes": [{"added": "myaddons@web.de", "field_name": "cc", "removed": ""}], "who": "myaddons@gmx.de", "when": "2011-10-07T13:49:51Z"}, {"changes": [{"removed": "", "field_name": "cc", "added": "bugzilla2007@duellmann24.net"}], "who": "bugzilla2007@duellmann24.net", "when": "2014-08-05T12:42:26Z"}, {"changes": [{"field_name": "status", "removed": "REOPENED", "added": "NEW"}], "who": "bugzilla2007@duellmann24.net", "when": "2014-08-05T12:42:39Z"}, {"who": "chrizilla@wolke7.net", "changes": [{"removed": "", "field_name": "cc", "added": "chrizilla@wolke7.net"}], "when": "2015-12-14T16:21:55Z"}], "id": 642782}]}